pycaret/__init__.py
pycaret/datasets.py
pycaret/distributions.py
pycaret/anomaly/__init__.py
pycaret/anomaly/functional.py
pycaret/anomaly/oop.py
pycaret/arules/__init__.py
pycaret/classification/__init__.py
pycaret/classification/functional.py
pycaret/classification/oop.py
pycaret/clustering/__init__.py
pycaret/clustering/functional.py
pycaret/clustering/oop.py
pycaret/containers/__init__.py
pycaret/containers/base_container.py
pycaret/containers/metrics/__init__.py
pycaret/containers/metrics/anomaly.py
pycaret/containers/metrics/base_metric.py
pycaret/containers/metrics/classification.py
pycaret/containers/metrics/clustering.py
pycaret/containers/metrics/regression.py
pycaret/containers/metrics/time_series.py
pycaret/containers/models/__init__.py
pycaret/containers/models/anomaly.py
pycaret/containers/models/base_model.py
pycaret/containers/models/classification.py
pycaret/containers/models/clustering.py
pycaret/containers/models/regression.py
pycaret/containers/models/time_series.py
pycaret/internal/Display.py
pycaret/internal/__init__.py
pycaret/internal/cuml_wrappers.py
pycaret/internal/distributions.py
pycaret/internal/ensemble.py
pycaret/internal/logging.py
pycaret/internal/meta_estimators.py
pycaret/internal/metrics.py
pycaret/internal/persistence.py
pycaret/internal/pipeline.py
pycaret/internal/tabular.py
pycaret/internal/tunable.py
pycaret/internal/utils.py
pycaret/internal/validation.py
pycaret/internal/patches/__init__.py
pycaret/internal/patches/boruta_py.py
pycaret/internal/patches/sklearn.py
pycaret/internal/patches/yellowbrick.py
pycaret/internal/plots/__init__.py
pycaret/internal/plots/helper.py
pycaret/internal/plots/residual_plots.py
pycaret/internal/plots/time_series.py
pycaret/internal/plots/yellowbrick.py
pycaret/internal/plots/utils/__init__.py
pycaret/internal/plots/utils/time_series.py
pycaret/internal/preprocess/__init__.py
pycaret/internal/preprocess/iterative_imputer.py
pycaret/internal/preprocess/preprocessor.py
pycaret_ts_alpha-3.0.0.dev1649017462.dist-info/LICENSE
pycaret_ts_alpha-3.0.0.dev1649017462.dist-info/METADATA
pycaret_ts_alpha-3.0.0.dev1649017462.dist-info/WHEEL
pycaret_ts_alpha-3.0.0.dev1649017462.dist-info/top_level.txt
pycaret_ts_alpha-3.0.0.dev1649017462.dist-info/RECORD
