Metadata-Version: 2.1
Name: pycaret-ts-alpha
Version: 3.0.0.dev1649017462
Summary: PyCaret - An open source, low-code machine learning library in Python.
Home-page: https://github.com/pycaret/pycaret
Author: Moez Ali
Author-email: moez.ali@queensu.ca
License: MIT
Platform: UNKNOWN
Classifier: License :: OSI Approved :: MIT License
Classifier: Programming Language :: Python :: 3.6
Classifier: Programming Language :: Python :: 3.7
Classifier: Programming Language :: Python :: 3.8
Classifier: Programming Language :: Python :: 3.9
Classifier: Topic :: Scientific/Engineering :: Artificial Intelligence
Classifier: License :: OSI Approved :: MIT License
Classifier: Operating System :: OS Independent
Requires-Python: >=3.7
License-File: LICENSE
Requires-Dist: ipython (>=5.5.0)
Requires-Dist: numpy (~=1.21)
Requires-Dist: pandas (<1.5.0,>=1.3.0)
Requires-Dist: scipy (~=1.7.3)
Requires-Dist: joblib (~=1.0.1)
Requires-Dist: scikit-learn (>=1.0.2)
Requires-Dist: pyod (>=0.9.8)
Requires-Dist: imbalanced-learn (>=0.8.1)
Requires-Dist: category-encoders (>=2.4.0)
Requires-Dist: lightgbm (>=3.0.0)
Requires-Dist: numba (~=0.55.0)
Requires-Dist: matplotlib (>=3.3.0)
Requires-Dist: scikit-plot (>=0.3.7)
Requires-Dist: yellowbrick (>=1.4)
Requires-Dist: plotly (>=5.0.0)
Requires-Dist: kaleido (>=0.2.1)
Requires-Dist: statsmodels (>=0.12.1)
Requires-Dist: sktime (==0.10.1)
Requires-Dist: tbats (>=1.1.0)
Requires-Dist: pmdarima (>=1.8.0)
Provides-Extra: analysis
Requires-Dist: shap (>=0.38.0) ; extra == 'analysis'
Requires-Dist: interpret (>=0.2.7) ; extra == 'analysis'
Requires-Dist: umap-learn (>=0.5.2) ; extra == 'analysis'
Requires-Dist: ipywidgets (>=7.6.5) ; extra == 'analysis'
Requires-Dist: pandas-profiling (>=3.1.0) ; extra == 'analysis'
Requires-Dist: explainerdashboard (>=0.3.8) ; extra == 'analysis'
Requires-Dist: autoviz (>=0.1.36) ; extra == 'analysis'
Requires-Dist: fairlearn (>=0.7.0) ; extra == 'analysis'
Provides-Extra: full
Requires-Dist: shap (>=0.38.0) ; extra == 'full'
Requires-Dist: interpret (>=0.2.7) ; extra == 'full'
Requires-Dist: umap-learn (>=0.5.2) ; extra == 'full'
Requires-Dist: ipywidgets (>=7.6.5) ; extra == 'full'
Requires-Dist: pandas-profiling (>=3.1.0) ; extra == 'full'
Requires-Dist: explainerdashboard (>=0.3.8) ; extra == 'full'
Requires-Dist: autoviz (>=0.1.36) ; extra == 'full'
Requires-Dist: fairlearn (>=0.7.0) ; extra == 'full'
Requires-Dist: xgboost (>=1.1.0) ; extra == 'full'
Requires-Dist: catboost (>=0.23.2) ; extra == 'full'
Requires-Dist: kmodes (>=0.11.1) ; extra == 'full'
Requires-Dist: mlxtend (>=0.19.0) ; extra == 'full'
Requires-Dist: tune-sklearn (>=0.2.1) ; extra == 'full'
Requires-Dist: ray[tune] (>=1.0.0) ; extra == 'full'
Requires-Dist: hyperopt (>=0.2.7) ; extra == 'full'
Requires-Dist: optuna (>=2.2.0) ; extra == 'full'
Requires-Dist: scikit-optimize (>=0.9.0) ; extra == 'full'
Requires-Dist: mlflow (>=1.24.0) ; extra == 'full'
Requires-Dist: gradio (>=2.8.10) ; extra == 'full'
Requires-Dist: fastapi (>=0.75.0) ; extra == 'full'
Requires-Dist: uvicorn (>=0.17.6) ; extra == 'full'
Requires-Dist: m2cgen (>=0.9.0) ; extra == 'full'
Requires-Dist: evidently (>=0.1.45.dev0) ; extra == 'full'
Requires-Dist: nltk (>=3.7) ; extra == 'full'
Requires-Dist: pyLDAvis (>=3.3.1) ; extra == 'full'
Requires-Dist: gensim (>=4.1.2) ; extra == 'full'
Requires-Dist: spacy (>=3.2.3) ; extra == 'full'
Requires-Dist: wordcloud (>=1.8.1) ; extra == 'full'
Requires-Dist: textblob (>=0.17.1) ; extra == 'full'
Requires-Dist: psutil (>=5.9.0) ; extra == 'full'
Requires-Dist: fugue (>=0.6.5) ; extra == 'full'
Provides-Extra: mlops
Requires-Dist: mlflow (>=1.24.0) ; extra == 'mlops'
Requires-Dist: gradio (>=2.8.10) ; extra == 'mlops'
Requires-Dist: fastapi (>=0.75.0) ; extra == 'mlops'
Requires-Dist: uvicorn (>=0.17.6) ; extra == 'mlops'
Requires-Dist: m2cgen (>=0.9.0) ; extra == 'mlops'
Requires-Dist: evidently (>=0.1.45.dev0) ; extra == 'mlops'
Provides-Extra: models
Requires-Dist: xgboost (>=1.1.0) ; extra == 'models'
Requires-Dist: catboost (>=0.23.2) ; extra == 'models'
Requires-Dist: kmodes (>=0.11.1) ; extra == 'models'
Requires-Dist: mlxtend (>=0.19.0) ; extra == 'models'
Provides-Extra: nlp
Requires-Dist: nltk (>=3.7) ; extra == 'nlp'
Requires-Dist: pyLDAvis (>=3.3.1) ; extra == 'nlp'
Requires-Dist: gensim (>=4.1.2) ; extra == 'nlp'
Requires-Dist: spacy (>=3.2.3) ; extra == 'nlp'
Requires-Dist: wordcloud (>=1.8.1) ; extra == 'nlp'
Requires-Dist: textblob (>=0.17.1) ; extra == 'nlp'
Provides-Extra: tuners
Requires-Dist: tune-sklearn (>=0.2.1) ; extra == 'tuners'
Requires-Dist: ray[tune] (>=1.0.0) ; extra == 'tuners'
Requires-Dist: hyperopt (>=0.2.7) ; extra == 'tuners'
Requires-Dist: optuna (>=2.2.0) ; extra == 'tuners'
Requires-Dist: scikit-optimize (>=0.9.0) ; extra == 'tuners'
